README.md
setup.py
choly/__init__.py
choly/__main__.py
choly.egg-info/PKG-INFO
choly.egg-info/SOURCES.txt
choly.egg-info/dependency_links.txt
choly.egg-info/entry_points.txt
choly.egg-info/requires.txt
choly.egg-info/top_level.txt
choly/commands/__init__.py
choly/commands/cli.py
choly/commands/core.py
choly/commands/envs.py
choly/commands/graal.py
choly/commands/template.py
choly/infrastructure/__init__.py
choly/infrastructure/log.py
choly/infrastructure/shell.py
choly/logic/__init__.py
choly/logic/envs.py
choly/logic/graal.py
choly/logic/shared.py
choly/logic/template.py
tests/__init__.py