Metadata-Version: 2.1
Name: choly
Version: 0.0.3
Summary: Holy Lambda Command Line Application
Home-page: https://github.com/FieryCod/holy-lambda
Author: Fierycod
Author-email: karol.wojcik@tuta.io
License: UNKNOWN
Platform: UNKNOWN
Classifier: Environment :: Console
Classifier: License :: OSI Approved :: MIT License
Classifier: Programming Language :: Python :: 3.7
